setup.py
xtesting_db_populate/__init__.py
xtesting_db_populate/api.py
xtesting_db_populate/config.py
xtesting_db_populate/output.py
xtesting_db_populate-1.3.2.data/scripts/xtesting-db-populate
xtesting_db_populate-1.3.2.dist-info/METADATA
xtesting_db_populate-1.3.2.dist-info/WHEEL
xtesting_db_populate-1.3.2.dist-info/top_level.txt
xtesting_db_populate-1.3.2.dist-info/RECORD
