Metadata-Version: 2.1
Name: xtesting-db-populate
Version: 1.3.2
Summary: xtesting db populate script
Home-page: https://gitlab.com/Orange-OpenSource/lfn/tools/xtesting-db-populate
Author: Orange OpenSource
License: Apache 2.0
Requires-Dist: pyyaml
Requires-Dist: requests
